mountainsort5/__init__.py
mountainsort5/core/SnippetClassifier.py
mountainsort5/core/Timer.py
mountainsort5/core/__init__.py
mountainsort5/core/compute_pca_features.py
mountainsort5/core/compute_templates.py
mountainsort5/core/detect_spikes.py
mountainsort5/core/extract_snippets.py
mountainsort5/core/get_block_recording_for_scheme3.py
mountainsort5/core/get_sampled_recording_for_training.py
mountainsort5/core/get_times_labels_from_sorting.py
mountainsort5/core/isosplit6_subdivision_method.py
mountainsort5/core/remove_duplicate_events.py
mountainsort5/quip/__init__.py
mountainsort5/quip/estimate_units.py
mountainsort5/schemes/Scheme1SortingParameters.py
mountainsort5/schemes/Scheme2SortingParameters.py
mountainsort5/schemes/Scheme3SortingParameters.py
mountainsort5/schemes/__init__.py
mountainsort5/schemes/sorting_scheme1.py
mountainsort5/schemes/sorting_scheme2.py
mountainsort5/schemes/sorting_scheme3.py
mountainsort5/util/TemporaryDirectory.py
mountainsort5/util/__init__.py
mountainsort5/util/binary_recording_io.py
mountainsort5/util/create_cached_recording.py
mountainsort5-0.5.8.dist-info/licenses/LICENSE
mountainsort5-0.5.8.dist-info/METADATA
mountainsort5-0.5.8.dist-info/WHEEL
mountainsort5-0.5.8.dist-info/top_level.txt
mountainsort5-0.5.8.dist-info/RECORD
