Metadata-Version: 2.4
Name: mountainsort5
Version: 0.5.8
Summary: MountainSort 5 spike sorting algorithm
Home-page: https://github.com/flatironinstitute/mountainsort5
Author: Jeremy Magland
Author-email: jmagland@flatironinstitute.org
License-File: LICENSE
Requires-Dist: spikeinterface>=0.97.1
Requires-Dist: isosplit6>=0.1.0
Requires-Dist: scikit-learn
Requires-Dist: packaging
Dynamic: author
Dynamic: author-email
Dynamic: description
Dynamic: description-content-type
Dynamic: home-page
Dynamic: license-file
Dynamic: requires-dist
Dynamic: summary
